drift/__init__.py
drift/api.py
drift/contacts.py
drift/conversations.py
drift/errors.py
drift/users.py
drift/utils.py
drift_python-1.1.1.dist-info/LICENSE
drift_python-1.1.1.dist-info/METADATA
drift_python-1.1.1.dist-info/WHEEL
drift_python-1.1.1.dist-info/top_level.txt
drift_python-1.1.1.dist-info/RECORD
