Metadata-Version: 2.1
Name: drift-python
Version: 1.1.1
Summary: A Simple Drift API Wrapper.
Home-page: https://github.com/Driftt/drift-python
Author: Drift Engineering
Author-email: driftintegrations@drift.com
License: MIT
Platform: UNKNOWN
Requires-Dist: requests (>=2.20.0)
